pymqttframework/__init__.py
pymqttframework/app.py
pymqttframework/callbacks.py
pymqttframework/config.py
pymqttframework/framework.py
pymqttframework/read_only_dict.py
pymqttframework-3.0.2.dist-info/METADATA
pymqttframework-3.0.2.dist-info/WHEEL
pymqttframework-3.0.2.dist-info/licenses/LICENSE
pymqttframework-3.0.2.dist-info/RECORD
