Metadata-Version: 2.4
Name: pymqttframework
Version: 3.0.2
Summary: Simple application framework for MQTT based applications
Author-email: Pauli Anttila <pauli.anttila@gmail.com>
License-File: LICENSE
Requires-Python: >=3.11
Requires-Dist: apscheduler==3.11.0
Requires-Dist: blinker==1.9.0
Requires-Dist: cheroot==10.0.1
Requires-Dist: click==8.2.1
Requires-Dist: deprecated==1.2.18
Requires-Dist: flask-limiter==3.12
Requires-Dist: flask-mqtt==1.2.1
Requires-Dist: flask==3.1.1
Requires-Dist: importlib-resources==6.5.2
Requires-Dist: itsdangerous==2.2.0
Requires-Dist: jaraco-functools==4.1.0
Requires-Dist: jinja2==3.1.6
Requires-Dist: limits==5.2.0
Requires-Dist: markdown-it-py==3.0.0
Requires-Dist: markupsafe==3.0.2
Requires-Dist: mdurl==0.1.2
Requires-Dist: more-itertools==10.7.0
Requires-Dist: ordered-set==4.1.0
Requires-Dist: packaging==24.2
Requires-Dist: paho-mqtt==1.6.1
Requires-Dist: prometheus-client==0.22.0
Requires-Dist: prometheus-flask-exporter==0.23.2
Requires-Dist: pygments==2.19.1
Requires-Dist: pytz==2025.2
Requires-Dist: rich==13.9.4
Requires-Dist: six==1.17.0
Requires-Dist: typing-extensions==4.13.2
Requires-Dist: tzlocal==5.3.1
Requires-Dist: werkzeug==3.1.3
Requires-Dist: wrapt==1.17.2
